sebsync.py
sebsync-1.0.13.dist-info/METADATA
sebsync-1.0.13.dist-info/WHEEL
sebsync-1.0.13.dist-info/entry_points.txt
sebsync-1.0.13.dist-info/licenses/AUTHORS
sebsync-1.0.13.dist-info/licenses/LICENSE
sebsync-1.0.13.dist-info/RECORD
