Metadata-Version: 2.4
Name: sebsync
Version: 1.0.13
Summary: Synchronize Standard Ebooks catalog with local EPUB collection.
Project-URL: Repository, https://github.com/pbryan/sebsync/
Author: Sebsync authors
License-File: AUTHORS
License-File: LICENSE
Keywords: book,download,ebook,standard,sync,synchronization
Classifier: Development Status :: 5 - Production/Stable
Classifier: Environment :: Console
Classifier: Intended Audience :: End Users/Desktop
Classifier: License :: OSI Approved :: Zero-Clause BSD (0BSD)
Classifier: Topic :: System :: Archiving :: Mirroring
Requires-Python: >=3.10
Requires-Dist: click
Requires-Dist: requests
